pod_whois/core.py
pod_whois-0.1.dist-info/LICENSE.md
pod_whois-0.1.dist-info/METADATA
pod_whois-0.1.dist-info/WHEEL
pod_whois-0.1.dist-info/entry_points.txt
pod_whois-0.1.dist-info/top_level.txt
pod_whois-0.1.dist-info/RECORD
