Metadata-Version: 2.1
Name: pod-whois
Version: 0.1
Summary: Babashka pod query whois info.
Home-page: https://github.com/ntestoc3/pod-whois
Author: ntestoc3
Author-email: ntoooooon@outlook.com
License: MIT
Keywords: babashka pod whois
Platform: UNKNOWN
Classifier: Development Status :: 3 - Alpha
Classifier: Intended Audience :: Developers
Classifier: License :: OSI Approved :: MIT License
Classifier: Programming Language :: Python :: 3
Classifier: Programming Language :: Python :: 3.6
Classifier: Programming Language :: Python :: 3.7
Classifier: Programming Language :: Python :: 3.8
Requires-Python: >=3.6, <4
Requires-Dist: bcoding
Requires-Dist: python-whois
Requires-Dist: ipwhois
Requires-Dist: retry
Requires-Dist: publicsuffix2
Requires-Dist: validators
